{"cs_c.md":"ede40031","cs_css.md":"0a6bbfdd","cs_command.md":"0c937583","cs_data structure _ algorithm.md":"487f58ca","cs_data structure.md":"5801c7d4","cs_git.md":"87c212aa","cs_github.md":"f272b94c","cs_html.md":"e79ed7a0","cs_java api.md":"7d1824ff","cs_java advance.md":"935648ad","cs_java framework.md":"3e3c42b5","cs_java.md":"071fae2f","cs_machine learning.md":"ea2f682b","cs_microsoft.md":"d0162930","cs_mysql.md":"c2e83649","cs_nosql.md":"a896c083","cs_operating system.md":"ad27cffd","cs_powershell.md":"d3ea9c52","cs_py web.md":"d7a98e40","index.md":"e76cc656","cs_c__.md":"49133548","cs_docker.md":"bbed3a43","cs_design patterns.md":"f25ad39d","contents.md":"154f27a2","software_api collections.md":"ff27de0f","software_chrome.md":"39162b85","software_application.md":"cc280f00","software_ffmpeg.md":"abe1825f","universal_markdown.md":"a9f1e594","software_micro office.md":"ed9f7d35","cs_spring.md":"c1ea1e65","universal_programming paradigm.md":"7f1edbd0","universal_qa.md":"10d8126d","universal_refactor 重构.md":"049ad80b","universal_regular expression.md":"480df3d6","universal_software.md":"0352c0fe","universal_terminology.md":"489f6c20","universal_uml.md":"4c823274","universal_security.md":"b7530877","universal_数据交换格式.md":"4326a4fb","universal_编码 _ 加密.md":"41ca9636","cs_javascript.md":"fbcb335b","cs_linux.md":"6d331990","cs_python lib.md":"66d50eed","cs_big data.md":"e5803302","cs_kubernetes.md":"20da9ce7","cs_pypi.md":"722b07a4","cs_algorithm.md":"d0a58740","cs_android sdk.md":"8ef60657","cs_bash.md":"a60bb3d6","cs_pythonic.md":"9c02857a","cs_web api.md":"be6170e3","cs_善假于键.md":"70495ac1","cs_vue.js.md":"e38e01aa","cs_windows.md":"6160e783","cs_注册表（registry）.md":"0b44e0fb","cs_vue ecosystem.md":"a5028798","cs_batch.md":"9684a2d6","cs_node.js.md":"891d63a0","cs_sql.md":"18584805","cs_网络（network）.md":"c843e2df","cs_android.md":"549077b9","cs_ssh.md":"f24da10e","cs_python.md":"9262b8f2"}
